piicatcher/__init__.py
piicatcher/api.py
piicatcher/command_line.py
piicatcher/dbinfo.py
piicatcher/detectors.py
piicatcher/generators.py
piicatcher/output.py
piicatcher/scanner.py
piicatcher-0.21.2.dist-info/LICENSE
piicatcher-0.21.2.dist-info/METADATA
piicatcher-0.21.2.dist-info/WHEEL
piicatcher-0.21.2.dist-info/entry_points.txt
piicatcher-0.21.2.dist-info/RECORD
