Metadata-Version: 2.1
Name: piicatcher
Version: 0.21.2
Summary: Find PII data in databases
Home-page: https://tokern.io/
License: Apache 2.0
Keywords: pii,postgres,snowflake,redshift,athena,bigquery
Author: Tokern
Author-email: info@tokern.io
Requires-Python: >=3.8,<=3.10.8
Classifier: Development Status :: 4 - Beta
Classifier: Intended Audience :: Developers
Classifier: License :: Other/Proprietary License
Classifier: Programming Language :: Python
Classifier: Programming Language :: Python :: 3
Classifier: Programming Language :: Python :: 3.8
Classifier: Programming Language :: Python :: 3.9
Classifier: Programming Language :: Python :: 3.10
Classifier: Topic :: Database
Classifier: Topic :: Software Development
Classifier: Topic :: Software Development :: Libraries :: Python Modules
Provides-Extra: datahub
Requires-Dist: acryl-datahub (>=0.8.16,<0.9.0) ; extra == "datahub"
Requires-Dist: catalogue (>=2.0.6,<3.0.0)
Requires-Dist: click
Requires-Dist: commonregex-improved (==1.0.2)
Requires-Dist: dataclasses (>=0.6) ; python_version >= "3.8" and python_version <= "3.10"
Requires-Dist: dbcat (==0.14.2)
Requires-Dist: goog-stats (>=0.1.2,<0.2.0)
Requires-Dist: google-cloud-bigquery-storage (==2.20.0)
Requires-Dist: great-expectations (>=0.13.42,<0.14.0) ; extra == "datahub"
Requires-Dist: python-json-logger (>=2.0.2,<3.0.0)
Requires-Dist: pyyaml
Requires-Dist: sqlalchemy-bigquery (==1.6.1)
Requires-Dist: tabulate (>=0.8.9,<0.9.0)
Requires-Dist: tqdm (>=4.62.3,<5.0.0)
Requires-Dist: typer (>=0.4.0,<0.5.0)
Project-URL: Repository, https://github.com/tokern/piicatcher/
